datavalues/__init__.py
datavalues/__version__.py
datavalues/data.py
datavalues/base/__init__.py
datavalues/base/core.py
datavalues/base/unit.py
datavalues/binary/__init__.py
datavalues/binary/base.py
datavalues/binary/bits.py
datavalues/binary/bytes.py
datavalues/metric/__init__.py
datavalues/metric/base.py
datavalues/metric/bits.py
datavalues/metric/bytes.py
datavalues-1.0.0.dist-info/licenses/LICENSE
datavalues-1.0.0.dist-info/METADATA
datavalues-1.0.0.dist-info/WHEEL
datavalues-1.0.0.dist-info/top_level.txt
datavalues-1.0.0.dist-info/RECORD
