Metadata-Version: 2.4
Name: datavalues
Version: 1.0.0
Summary: Package for converting data units
Author-email: Ben Nassif <bennassif@gmail.com>
License-Expression: MIT
Project-URL: homepage, https://github.com/bnassif/datavalues
Project-URL: issues, https://github.com/bnassif/datavalues/issues
Keywords: conversion,data,units,byte,helper
Classifier: Intended Audience :: Developers
Classifier: Natural Language :: English
Classifier: Operating System :: OS Independent
Classifier: Topic :: Software Development
Classifier: Programming Language :: Python :: 3
Requires-Python: >=3.10
License-File: LICENSE
Dynamic: license-file
